README.rst
setup.cfg
setup.py
dAwebAPI/PathStr.py
dAwebAPI/SeizedCom.py
dAwebAPI/WebAPI.py
dAwebAPI/__init__.py
dAwebAPI/parseArgStr.py
dAwebAPI/types.py
dAwebAPI.egg-info/PKG-INFO
dAwebAPI.egg-info/SOURCES.txt
dAwebAPI.egg-info/dependency_links.txt
dAwebAPI.egg-info/top_level.txt