Metadata-Version: 1.1
Name: dAwebAPI
Version: 0.2
Summary: A Python library to access dA-compatible webAPIs
Home-page: https://github.com/radjkarl/daWebApi
Author: Karl Bedrich
Author-email: karl.bedrich@nus.edu.sg
License: GPL v3
Platform: UNKNOWN
Classifier: Development Status :: 3 - Alpha
Classifier: Environment :: Web Environment
Classifier: Intended Audience :: Developers
Classifier: Intended Audience :: Science/Research
Classifier: Intended Audience :: Other Audience
Classifier: License :: OSI Approved :: GNU General Public License (GPL)
Classifier: Operating System :: OS Independent
Classifier: Programming Language :: Python
Classifier: Topic :: Software Development :: Libraries :: Python Modules
